{
  "schema_version": "operational_governance.v1",
  "governance_only": true,
  "design_only": true,
  "architecture_only": true,
  "research_only": true,
  "local_only": true,
  "category_id": "review_boards",
  "title": "Review Boards",
  "status": "موثق",
  "items": [
    {
      "schema_version": "operational_governance.v1",
      "governance_only": true,
      "design_only": true,
      "architecture_only": true,
      "research_only": true,
      "local_only": true,
      "item_id": "REVIEW_BOARDS-01",
      "title": "Architecture Review Board",
      "description": "Governance-only framework item for architecture review board.",
      "category": "review_boards",
      "priority": "مرتفع",
      "status": "موثق",
      "implementation_allowed_now": false,
      "future_program_required": true,
      "safety_notes": [
        "Governance artifact only.",
        "No runtime control or external connectivity is allowed."
      ],
      "verification_method": "governance review"
    },
    {
      "schema_version": "operational_governance.v1",
      "governance_only": true,
      "design_only": true,
      "architecture_only": true,
      "research_only": true,
      "local_only": true,
      "item_id": "REVIEW_BOARDS-02",
      "title": "Risk Review Board",
      "description": "Governance-only framework item for risk review board.",
      "category": "review_boards",
      "priority": "مرتفع",
      "status": "موثق",
      "implementation_allowed_now": false,
      "future_program_required": true,
      "safety_notes": [
        "Governance artifact only.",
        "No runtime control or external connectivity is allowed."
      ],
      "verification_method": "governance review"
    },
    {
      "schema_version": "operational_governance.v1",
      "governance_only": true,
      "design_only": true,
      "architecture_only": true,
      "research_only": true,
      "local_only": true,
      "item_id": "REVIEW_BOARDS-03",
      "title": "Compliance Review Board",
      "description": "Governance-only framework item for compliance review board.",
      "category": "review_boards",
      "priority": "متوسط",
      "status": "موثق",
      "implementation_allowed_now": false,
      "future_program_required": true,
      "safety_notes": [
        "Governance artifact only.",
        "No runtime control or external connectivity is allowed."
      ],
      "verification_method": "governance review"
    },
    {
      "schema_version": "operational_governance.v1",
      "governance_only": true,
      "design_only": true,
      "architecture_only": true,
      "research_only": true,
      "local_only": true,
      "item_id": "REVIEW_BOARDS-04",
      "title": "Operations Review Board",
      "description": "Governance-only framework item for operations review board.",
      "category": "review_boards",
      "priority": "متوسط",
      "status": "موثق",
      "implementation_allowed_now": false,
      "future_program_required": true,
      "safety_notes": [
        "Governance artifact only.",
        "No runtime control or external connectivity is allowed."
      ],
      "verification_method": "governance review"
    },
    {
      "schema_version": "operational_governance.v1",
      "governance_only": true,
      "design_only": true,
      "architecture_only": true,
      "research_only": true,
      "local_only": true,
      "item_id": "REVIEW_BOARDS-05",
      "title": "Release Review Board",
      "description": "Governance-only framework item for release review board.",
      "category": "review_boards",
      "priority": "متوسط",
      "status": "موثق",
      "implementation_allowed_now": false,
      "future_program_required": true,
      "safety_notes": [
        "Governance artifact only.",
        "No runtime control or external connectivity is allowed."
      ],
      "verification_method": "governance review"
    },
    {
      "schema_version": "operational_governance.v1",
      "governance_only": true,
      "design_only": true,
      "architecture_only": true,
      "research_only": true,
      "local_only": true,
      "item_id": "REVIEW_BOARDS-06",
      "title": "Incident Review Board",
      "description": "Governance-only framework item for incident review board.",
      "category": "review_boards",
      "priority": "متوسط",
      "status": "موثق",
      "implementation_allowed_now": false,
      "future_program_required": true,
      "safety_notes": [
        "Governance artifact only.",
        "No runtime control or external connectivity is allowed."
      ],
      "verification_method": "governance review"
    }
  ]
}